growattServerSR/__init__.py
growattServerSR/growattServerSR.py
growattServerSR/growattServerSR_test.py
growattServerSR-1.7.4.dist-info/LICENSE
growattServerSR-1.7.4.dist-info/METADATA
growattServerSR-1.7.4.dist-info/WHEEL
growattServerSR-1.7.4.dist-info/top_level.txt
growattServerSR-1.7.4.dist-info/RECORD
