Metadata-Version: 2.1
Name: growattServerSR
Version: 1.7.4
Summary: A package to talk to growatt server - forked from the original by @indykoning
Home-page: https://github.com/simonrankine/PyPi_GrowattServer
Author: Simon Rankine
Author-email: simon@srankine.uk
License: MIT
Platform: UNKNOWN
Classifier: Programming Language :: Python :: 3
Classifier: License :: OSI Approved :: MIT License
Classifier: Operating System :: OS Independent
License-File: LICENSE
Requires-Dist: requests
